myapp/__init__.py
myapp/admin.py
myapp/apps.py
myapp/models.py
myapp/tests.py
myapp/views.py
django_myapp-0.1.dist-info/LICENSE
django_myapp-0.1.dist-info/METADATA
django_myapp-0.1.dist-info/WHEEL
django_myapp-0.1.dist-info/top_level.txt
django_myapp-0.1.dist-info/RECORD
